pycli_todo/__init__.py
pycli_todo/pytodo.py
pycli_todo-1.0.1.dist-info/entry_points.txt
pycli_todo-1.0.1.dist-info/WHEEL
pycli_todo-1.0.1.dist-info/METADATA
pycli_todo-1.0.1.dist-info/RECORD
